my_tool.py
app/__init__.py
app/__main__.py
app/application.py
app/attendance.py
app/cumulative_count.py
app/enrollment.py
app/personal_info_all_data.py
bgcombine-1.0.9.dist-info/LICENSE
bgcombine-1.0.9.dist-info/METADATA
bgcombine-1.0.9.dist-info/WHEEL
bgcombine-1.0.9.dist-info/entry_points.txt
bgcombine-1.0.9.dist-info/top_level.txt
bgcombine-1.0.9.dist-info/RECORD
