Metadata-Version: 2.1
Name: bgcombine
Version: 1.0.9
Summary: BGC Combiner is a tool for transforming and combining data from ProCare.
Home-page: https://github.com/dommiller88/bgcombine
Author: Dominic Miller
Author-email: dommiller88@gmail.com
License: MIT
Classifier: Programming Language :: Python :: 3.7
Classifier: Operating System :: OS Independent
Requires-Python: >=3.7
License-File: LICENSE
Requires-Dist: click (>=7.1.2)
Requires-Dist: pandas (>=1.3.5)
Requires-Dist: openpyxl (>=3.0.0)
